{
  "dataset": "Trashnet",
  "image": {
    "width": 4032,
    "height": 3024,
    "original_filename": "paper249.jpg",
    "filename": "paper249.jpg",
    "url": "https://darwin.v7labs.com/api/images/243163459/original",
    "thumbnail_url": "https://darwin.v7labs.com/api/images/243163459/thumbnail",
    "path": "/",
    "workview_url": "https://darwin.v7labs.com/workview?dataset=386745&image=455"
  },
  "annotations": [
    {
      "bounding_box": {
        "h": 1693.0,
        "w": 2151.0,
        "x": 1392.0,
        "y": 719.0
      },
      "name": "paper",
      "polygon": {
        "path": [
          {
            "x": 1411.0,
            "y": 738.0
          },
          {
            "x": 1411.0,
            "y": 747.0
          },
          {
            "x": 1410.0,
            "y": 748.0
          },
          {
            "x": 1406.0,
            "y": 748.0
          },
          {
            "x": 1406.0,
            "y": 761.0
          },
          {
            "x": 1405.0,
            "y": 762.0
          },
          {
            "x": 1401.0,
            "y": 762.0
          },
          {
            "x": 1401.0,
            "y": 1016.0
          },
          {
            "x": 1.4e3,
            "y": 1017.0
          },
          {
            "x": 1396.0,
            "y": 1017.0
          },
          {
            "x": 1396.0,
            "y": 1456.0
          },
          {
            "x": 1.4e3,
            "y": 1456.0
          },
          {
            "x": 1401.0,
            "y": 1457.0
          },
          {
            "x": 1401.0,
            "y": 1593.0
          },
          {
            "x": 1.4e3,
            "y": 1594.0
          },
          {
            "x": 1396.0,
            "y": 1594.0
          },
          {
            "x": 1396.0,
            "y": 1802.0
          },
          {
            "x": 1.4e3,
            "y": 1802.0
          },
          {
            "x": 1401.0,
            "y": 1803.0
          },
          {
            "x": 1401.0,
            "y": 1863.0
          },
          {
            "x": 1.4e3,
            "y": 1864.0
          },
          {
            "x": 1396.0,
            "y": 1864.0
          },
          {
            "x": 1396.0,
            "y": 2014.0
          },
          {
            "x": 1395.0,
            "y": 2015.0
          },
          {
            "x": 1392.0,
            "y": 2015.0
          },
          {
            "x": 1392.0,
            "y": 2100
          },
          {
            "x": 1395.0,
            "y": 2100
          },
          {
            "x": 1396.0,
            "y": 2101.0
          },
          {
            "x": 1396.0,
            "y": 2152.0
          },
          {
            "x": 1395.0,
            "y": 2153.0
          },
          {
            "x": 1392.0,
            "y": 2153.0
          },
          {
            "x": 1392.0,
            "y": 2327.0
          },
          {
            "x": 1395.0,
            "y": 2327.0
          },
          {
            "x": 1396.0,
            "y": 2328.0
          },
          {
            "x": 1396.0,
            "y": 2341.0
          },
          {
            "x": 1.4e3,
            "y": 2341.0
          },
          {
            "x": 1401.0,
            "y": 2342.0
          },
          {
            "x": 1401.0,
            "y": 2350.0
          },
          {
            "x": 1405.0,
            "y": 2350.0
          },
          {
            "x": 1406.0,
            "y": 2351.0
          },
          {
            "x": 1406.0,
            "y": 2355.0
          },
          {
            "x": 1410.0,
            "y": 2355.0
          },
          {
            "x": 1411.0,
            "y": 2356.0
          },
          {
            "x": 1411.0,
            "y": 2364.0
          },
          {
            "x": 1419.0,
            "y": 2364.0
          },
          {
            "x": 1420.0,
            "y": 2365.0
          },
          {
            "x": 1420.0,
            "y": 2369.0
          },
          {
            "x": 1424.0,
            "y": 2369.0
          },
          {
            "x": 1425.0,
            "y": 2370.0
          },
          {
            "x": 1425.0,
            "y": 2374.0
          },
          {
            "x": 1438.0,
            "y": 2374.0
          },
          {
            "x": 1439.0,
            "y": 2375.0
          },
          {
            "x": 1439.0,
            "y": 2379.0
          },
          {
            "x": 1532.0,
            "y": 2379.0
          },
          {
            "x": 1533.0,
            "y": 2380.0
          },
          {
            "x": 1533.0,
            "y": 2383.0
          },
          {
            "x": 1594.0,
            "y": 2383.0
          },
          {
            "x": 1594.0,
            "y": 2380.0
          },
          {
            "x": 1595.0,
            "y": 2379.0
          },
          {
            "x": 1679.0,
            "y": 2379.0
          },
          {
            "x": 1679.0,
            "y": 2375.0
          },
          {
            "x": 1680.0,
            "y": 2374.0
          },
          {
            "x": 1797.0,
            "y": 2374.0
          },
          {
            "x": 1798.0,
            "y": 2375.0
          },
          {
            "x": 1798.0,
            "y": 2379.0
          },
          {
            "x": 1849.0,
            "y": 2379.0
          },
          {
            "x": 1849.0,
            "y": 2375.0
          },
          {
            "x": 1850.0,
            "y": 2374.0
          },
          {
            "x": 1901.0,
            "y": 2374.0
          },
          {
            "x": 1901.0,
            "y": 2370.0
          },
          {
            "x": 1902.0,
            "y": 2369.0
          },
          {
            "x": 2067.0,
            "y": 2369.0
          },
          {
            "x": 2068.0,
            "y": 2370.0
          },
          {
            "x": 2068.0,
            "y": 2374.0
          },
          {
            "x": 2086.0,
            "y": 2374.0
          },
          {
            "x": 2087.0,
            "y": 2375.0
          },
          {
            "x": 2087.0,
            "y": 2379.0
          },
          {
            "x": 2100,
            "y": 2379.0
          },
          {
            "x": 2101.0,
            "y": 2380.0
          },
          {
            "x": 2101.0,
            "y": 2383.0
          },
          {
            "x": 2138.0,
            "y": 2383.0
          },
          {
            "x": 2139.0,
            "y": 2384.0
          },
          {
            "x": 2139.0,
            "y": 2388.0
          },
          {
            "x": 2237.0,
            "y": 2388.0
          },
          {
            "x": 2238.0,
            "y": 2389.0
          },
          {
            "x": 2238.0,
            "y": 2393.0
          },
          {
            "x": 2294.0,
            "y": 2393.0
          },
          {
            "x": 2295.0,
            "y": 2394.0
          },
          {
            "x": 2295.0,
            "y": 2398.0
          },
          {
            "x": 2337.0,
            "y": 2398.0
          },
          {
            "x": 2337.0,
            "y": 2394.0
          },
          {
            "x": 2338.0,
            "y": 2393.0
          },
          {
            "x": 2365.0,
            "y": 2393.0
          },
          {
            "x": 2365.0,
            "y": 2389.0
          },
          {
            "x": 2366.0,
            "y": 2388.0
          },
          {
            "x": 2393.0,
            "y": 2388.0
          },
          {
            "x": 2393.0,
            "y": 2384.0
          },
          {
            "x": 2394.0,
            "y": 2383.0
          },
          {
            "x": 2417.0,
            "y": 2383.0
          },
          {
            "x": 2417.0,
            "y": 2380.0
          },
          {
            "x": 2418.0,
            "y": 2379.0
          },
          {
            "x": 2460.0,
            "y": 2379.0
          },
          {
            "x": 2461.0,
            "y": 2380.0
          },
          {
            "x": 2461.0,
            "y": 2383.0
          },
          {
            "x": 2478.0,
            "y": 2383.0
          },
          {
            "x": 2479.0,
            "y": 2384.0
          },
          {
            "x": 2479.0,
            "y": 2388.0
          },
          {
            "x": 2530.0,
            "y": 2388.0
          },
          {
            "x": 2531.0,
            "y": 2389.0
          },
          {
            "x": 2531.0,
            "y": 2393.0
          },
          {
            "x": 2890.0,
            "y": 2393.0
          },
          {
            "x": 2891.0,
            "y": 2394.0
          },
          {
            "x": 2891.0,
            "y": 2398.0
          },
          {
            "x": 2918.0,
            "y": 2398.0
          },
          {
            "x": 2918.0,
            "y": 2394.0
          },
          {
            "x": 2919.0,
            "y": 2393.0
          },
          {
            "x": 3003.0,
            "y": 2393.0
          },
          {
            "x": 3004.0,
            "y": 2394.0
          },
          {
            "x": 3004.0,
            "y": 2398.0
          },
          {
            "x": 3117.0,
            "y": 2398.0
          },
          {
            "x": 3118.0,
            "y": 2399.0
          },
          {
            "x": 3118.0,
            "y": 2402.0
          },
          {
            "x": 3164.0,
            "y": 2402.0
          },
          {
            "x": 3165.0,
            "y": 2403.0
          },
          {
            "x": 3165.0,
            "y": 2407.0
          },
          {
            "x": 3330.0,
            "y": 2407.0
          },
          {
            "x": 3331.0,
            "y": 2408.0
          },
          {
            "x": 3331.0,
            "y": 2412.0
          },
          {
            "x": 3387.0,
            "y": 2412.0
          },
          {
            "x": 3387.0,
            "y": 2408.0
          },
          {
            "x": 3388.0,
            "y": 2407.0
          },
          {
            "x": 3448.0,
            "y": 2407.0
          },
          {
            "x": 3448.0,
            "y": 2403.0
          },
          {
            "x": 3449.0,
            "y": 2402.0
          },
          {
            "x": 3481.0,
            "y": 2402.0
          },
          {
            "x": 3482.0,
            "y": 2403.0
          },
          {
            "x": 3482.0,
            "y": 2407.0
          },
          {
            "x": 3495.0,
            "y": 2407.0
          },
          {
            "x": 3495.0,
            "y": 2403.0
          },
          {
            "x": 3496.0,
            "y": 2402.0
          },
          {
            "x": 3519.0,
            "y": 2402.0
          },
          {
            "x": 3519.0,
            "y": 2399.0
          },
          {
            "x": 3520.0,
            "y": 2398.0
          },
          {
            "x": 3528.0,
            "y": 2398.0
          },
          {
            "x": 3528.0,
            "y": 2394.0
          },
          {
            "x": 3529.0,
            "y": 2393.0
          },
          {
            "x": 3533.0,
            "y": 2393.0
          },
          {
            "x": 3533.0,
            "y": 2389.0
          },
          {
            "x": 3534.0,
            "y": 2388.0
          },
          {
            "x": 3538.0,
            "y": 2388.0
          },
          {
            "x": 3538.0,
            "y": 2375.0
          },
          {
            "x": 3539.0,
            "y": 2374.0
          },
          {
            "x": 3543.0,
            "y": 2374.0
          },
          {
            "x": 3543.0,
            "y": 2318.0
          },
          {
            "x": 3539.0,
            "y": 2318.0
          },
          {
            "x": 3538.0,
            "y": 2317.0
          },
          {
            "x": 3538.0,
            "y": 2190.0
          },
          {
            "x": 3534.0,
            "y": 2190.0
          },
          {
            "x": 3533.0,
            "y": 2189.0
          },
          {
            "x": 3533.0,
            "y": 2101.0
          },
          {
            "x": 3529.0,
            "y": 2101.0
          },
          {
            "x": 3528.0,
            "y": 2100
          },
          {
            "x": 3528.0,
            "y": 2049.0
          },
          {
            "x": 3529.0,
            "y": 2048.0
          },
          {
            "x": 3533.0,
            "y": 2048.0
          },
          {
            "x": 3533.0,
            "y": 1746.0
          },
          {
            "x": 3529.0,
            "y": 1746.0
          },
          {
            "x": 3528.0,
            "y": 1745.0
          },
          {
            "x": 3528.0,
            "y": 1732.0
          },
          {
            "x": 3529.0,
            "y": 1731.0
          },
          {
            "x": 3533.0,
            "y": 1731.0
          },
          {
            "x": 3533.0,
            "y": 1093.0
          },
          {
            "x": 3534.0,
            "y": 1092.0
          },
          {
            "x": 3538.0,
            "y": 1092.0
          },
          {
            "x": 3538.0,
            "y": 947.0
          },
          {
            "x": 3539.0,
            "y": 946.0
          },
          {
            "x": 3543.0,
            "y": 946.0
          },
          {
            "x": 3543.0,
            "y": 771.0
          },
          {
            "x": 3539.0,
            "y": 771.0
          },
          {
            "x": 3538.0,
            "y": 770.0
          },
          {
            "x": 3538.0,
            "y": 757.0
          },
          {
            "x": 3534.0,
            "y": 757.0
          },
          {
            "x": 3533.0,
            "y": 756.0
          },
          {
            "x": 3533.0,
            "y": 748.0
          },
          {
            "x": 3529.0,
            "y": 748.0
          },
          {
            "x": 3528.0,
            "y": 747.0
          },
          {
            "x": 3528.0,
            "y": 743.0
          },
          {
            "x": 3525.0,
            "y": 743.0
          },
          {
            "x": 3524.0,
            "y": 742.0
          },
          {
            "x": 3524.0,
            "y": 738.0
          },
          {
            "x": 3520.0,
            "y": 738.0
          },
          {
            "x": 3519.0,
            "y": 737.0
          },
          {
            "x": 3519.0,
            "y": 734.0
          },
          {
            "x": 3511.0,
            "y": 734.0
          },
          {
            "x": 3510.0,
            "y": 733.0
          },
          {
            "x": 3510.0,
            "y": 729.0
          },
          {
            "x": 3492.0,
            "y": 729.0
          },
          {
            "x": 3491.0,
            "y": 728.0
          },
          {
            "x": 3491.0,
            "y": 724.0
          },
          {
            "x": 3463.0,
            "y": 724.0
          },
          {
            "x": 3463.0,
            "y": 728.0
          },
          {
            "x": 3462.0,
            "y": 729.0
          },
          {
            "x": 3227.0,
            "y": 729.0
          },
          {
            "x": 3226.0,
            "y": 728.0
          },
          {
            "x": 3226.0,
            "y": 724.0
          },
          {
            "x": 3075.0,
            "y": 724.0
          },
          {
            "x": 3074.0,
            "y": 723.0
          },
          {
            "x": 3074.0,
            "y": 719.0
          },
          {
            "x": 3071.0,
            "y": 719.0
          },
          {
            "x": 3071.0,
            "y": 723.0
          },
          {
            "x": 3070.0,
            "y": 724.0
          },
          {
            "x": 2744.0,
            "y": 724.0
          },
          {
            "x": 2744.0,
            "y": 728.0
          },
          {
            "x": 2743.0,
            "y": 729.0
          },
          {
            "x": 2352.0,
            "y": 729.0
          },
          {
            "x": 2351.0,
            "y": 728.0
          },
          {
            "x": 2351.0,
            "y": 724.0
          },
          {
            "x": 2304.0,
            "y": 724.0
          },
          {
            "x": 2304.0,
            "y": 728.0
          },
          {
            "x": 2303.0,
            "y": 729.0
          },
          {
            "x": 2148.0,
            "y": 729.0
          },
          {
            "x": 2147.0,
            "y": 728.0
          },
          {
            "x": 2147.0,
            "y": 724.0
          },
          {
            "x": 1884.0,
            "y": 724.0
          },
          {
            "x": 1884.0,
            "y": 728.0
          },
          {
            "x": 1883.0,
            "y": 729.0
          },
          {
            "x": 1860.0,
            "y": 729.0
          },
          {
            "x": 1860.0,
            "y": 733.0
          },
          {
            "x": 1859.0,
            "y": 734.0
          },
          {
            "x": 1850.0,
            "y": 734.0
          },
          {
            "x": 1850.0,
            "y": 737.0
          },
          {
            "x": 1849.0,
            "y": 738.0
          },
          {
            "x": 1846.0,
            "y": 738.0
          },
          {
            "x": 1845.0,
            "y": 737.0
          },
          {
            "x": 1845.0,
            "y": 734.0
          },
          {
            "x": 1822.0,
            "y": 734.0
          },
          {
            "x": 1821.0,
            "y": 733.0
          },
          {
            "x": 1821.0,
            "y": 729.0
          },
          {
            "x": 1765.0,
            "y": 729.0
          },
          {
            "x": 1764.0,
            "y": 728.0
          },
          {
            "x": 1764.0,
            "y": 724.0
          },
          {
            "x": 1.5e3,
            "y": 724.0
          },
          {
            "x": 1499.0,
            "y": 723.0
          },
          {
            "x": 1499.0,
            "y": 719.0
          },
          {
            "x": 1444.0,
            "y": 719.0
          },
          {
            "x": 1444.0,
            "y": 723.0
          },
          {
            "x": 1443.0,
            "y": 724.0
          },
          {
            "x": 1429.0,
            "y": 724.0
          },
          {
            "x": 1429.0,
            "y": 728.0
          },
          {
            "x": 1428.0,
            "y": 729.0
          },
          {
            "x": 1420.0,
            "y": 729.0
          },
          {
            "x": 1420.0,
            "y": 733.0
          },
          {
            "x": 1419.0,
            "y": 734.0
          },
          {
            "x": 1415.0,
            "y": 734.0
          },
          {
            "x": 1415.0,
            "y": 737.0
          },
          {
            "x": 1414.0,
            "y": 738.0
          }
        ]
      }
    }
  ]
}